nagios_taskserver_plugin/__init__.py
nagios_taskserver_plugin/cmdline.py
nagios_taskserver_plugin/commands.py
nagios_taskserver_plugin/exceptions.py
nagios_taskserver_plugin/output.py
nagios_taskserver_plugin/utils.py
nagios_taskserver_plugin-0.6.0.dist-info/METADATA
nagios_taskserver_plugin-0.6.0.dist-info/WHEEL
nagios_taskserver_plugin-0.6.0.dist-info/entry_points.txt
nagios_taskserver_plugin-0.6.0.dist-info/top_level.txt
nagios_taskserver_plugin-0.6.0.dist-info/RECORD
