Metadata-Version: 2.1
Name: nagios-taskserver-plugin
Version: 0.6.0
Summary: Monitor taskserver (taskd) using Nagios.
Home-page: https://github.com/coddingtonbear/nagios-taskserver-plugin
Author: Adam Coddington
Author-email: me@adamcoddington.net
License: UNKNOWN
Platform: UNKNOWN
Classifier: License :: OSI Approved :: MIT License
Classifier: Operating System :: OS Independent
Classifier: Programming Language :: Python :: 3
Requires-Dist: argparse
